MANIFEST.in
README.rst
setup.cfg
setup.py
colorterm/__init__.py
colorterm/colorterm.py
colorterm/table.py
colorterm.egg-info/PKG-INFO
colorterm.egg-info/SOURCES.txt
colorterm.egg-info/dependency_links.txt
colorterm.egg-info/entry_points.txt
colorterm.egg-info/not-zip-safe
colorterm.egg-info/top_level.txt
tests/__init__.py
tests/test_colorterm.py
tests/test_table.py